[{"range":"A1","value":"name","columnWidth":128,"columnNumber":1,"fontWeight":"bold","horizontalAlignment":"left"},{"range":"B1","value":"asset","columnWidth":100,"columnNumber":2,"fontWeight":"bold","horizontalAlignment":"left"},{"range":"C1","value":"skyboxsize","columnWidth":100,"columnNumber":3,"fontWeight":"bold","horizontalAlignment":"left"},{"range":"D1","value":"skybox","columnWidth":100,"columnNumber":4,"fontWeight":"bold","horizontalAlignment":"left"},{"range":"E1","value":"width","columnWidth":100,"columnNumber":5,"fontWeight":"bold","horizontalAlignment":"left"},{"range":"F1","value":"height","columnWidth":100,"columnNumber":6,"fontWeight":"bold","horizontalAlignment":"left"},{"range":"G1","value":"depth","columnWidth":100,"columnNumber":7,"fontWeight":"bold","horizontalAlignment":"left"},{"columnWidth":100,"columnNumber":8,"horizontalAlignment":"general"},{"columnWidth":100,"columnNumber":9,"horizontalAlignment":"general"},{"columnWidth":100,"columnNumber":10,"horizontalAlignment":"general"},{"columnWidth":100,"columnNumber":11,"horizontalAlignment":"general"},{"columnWidth":100,"columnNumber":12,"horizontalAlignment":"general"},{"columnWidth":100,"columnNumber":13,"horizontalAlignment":"general"},{"columnWidth":100,"columnNumber":14,"horizontalAlignment":"general"},{"columnWidth":100,"columnNumber":15,"horizontalAlignment":"general"},{"columnWidth":100,"columnNumber":16,"horizontalAlignment":"general"},{"columnWidth":100,"columnNumber":17,"horizontalAlignment":"general"},{"columnWidth":100,"columnNumber":18,"horizontalAlignment":"general"},{"columnWidth":100,"columnNumber":19,"horizontalAlignment":"general"},{"columnWidth":100,"columnNumber":20,"horizontalAlignment":"general"},{"columnWidth":100,"columnNumber":21,"horizontalAlignment":"general"},{"range":"A2","value":"Wine Display","horizontalAlignment":"left"},{"range":"B2","value":"sceneblock","horizontalAlignment":"left"},{"range":"C2","value":800,"horizontalAlignment":"left"},{"range":"D2","value":"sb:photo360/outside2360.jpg","horizontalAlignment":"left"},{"range":"E2","value":800,"horizontalAlignment":"left"},{"range":"F2","value":800,"horizontalAlignment":"left"},{"range":"G2","value":800,"horizontalAlignment":"left"},{"range":"A4","value":"name","fontWeight":"bold"},{"range":"B4","value":"asset","fontWeight":"bold"},{"range":"A5","value":"wine1block"},{"range":"B5","value":"block"},{"range":"A6","value":"wine12block"},{"range":"B6","value":"block"},{"range":"A7","value":"wine13block"},{"range":"B7","value":"block"},{"range":"A8","value":"wine14block"},{"range":"B8","value":"block"},{"range":"A9","value":"wine2block"},{"range":"B9","value":"block"},{"range":"A10","value":"wineblock22"},{"range":"B10","value":"block"},{"range":"A11","value":"wineblock23"},{"range":"B11","value":"block"},{"range":"A12","value":"wineblock24"},{"range":"B12","value":"block"},{"range":"A13","value":"wineblock4"},{"range":"B13","value":"block"},{"range":"A14","value":"wineblock42"},{"range":"B14","value":"block"},{"range":"A15","value":"wineblock43"},{"range":"B15","value":"block"},{"range":"A16","value":"wineblock44"},{"range":"B16","value":"block"},{"range":"A17","value":"wineblock5"},{"range":"B17","value":"block"},{"range":"A18","value":"wineblock52"},{"range":"B18","value":"block"},{"range":"A19","value":"wineblock53"},{"range":"B19","value":"block"},{"range":"A20","value":"wineblock7"},{"range":"B20","value":"block"},{"range":"A21","value":"wineblock72"},{"range":"B21","value":"block"},{"range":"A22","value":"wineblock73"},{"range":"B22","value":"block"},{"range":"A23","value":"wineblock74"},{"range":"B23","value":"block"},{"range":"A25","value":"name","fontWeight":"bold","horizontalAlignment":"left"},{"range":"B25","value":"asset","fontWeight":"bold","horizontalAlignment":"left"},{"range":"C25","value":"meshpath","fontWeight":"bold","horizontalAlignment":"left"},{"range":"D25","value":"texturepath","fontWeight":"bold","horizontalAlignment":"left"},{"range":"E25","value":"bmppath","fontWeight":"bold","horizontalAlignment":"left"},{"range":"F25","value":"emissivepath","fontWeight":"bold","horizontalAlignment":"left"},{"range":"G25","value":"specularpath","fontWeight":"bold","horizontalAlignment":"left"},{"range":"H25","value":"specularpower","fontWeight":"bold","horizontalAlignment":"left"},{"range":"I25","value":"hasalpha","fontWeight":"bold","horizontalAlignment":"left"},{"range":"J25","formula":"=colorColumn(\"materialname\")","fontWeight":"bold","horizontalAlignment":"left"},{"range":"K25","value":"parent","fontWeight":"bold","horizontalAlignment":"left"},{"range":"L25","value":"visibility","fontWeight":"bold","horizontalAlignment":"left"},{"range":"M25","value":"x","fontWeight":"bold","horizontalAlignment":"left"},{"range":"N25","value":"y","fontWeight":"bold","horizontalAlignment":"left"},{"range":"O25","value":"z","fontWeight":"bold","horizontalAlignment":"left"},{"range":"P25","value":"rx","fontWeight":"bold","horizontalAlignment":"left"},{"range":"Q25","value":"ry","fontWeight":"bold","horizontalAlignment":"left"},{"range":"R25","value":"rz","fontWeight":"bold","horizontalAlignment":"left"},{"range":"S25","value":"sx","fontWeight":"bold","horizontalAlignment":"left"},{"range":"T25","value":"sy","fontWeight":"bold","horizontalAlignment":"left"},{"range":"U25","value":"sz","fontWeight":"bold","horizontalAlignment":"left"},{"range":"A26","value":"winemesha001","fontColor":"#222222","horizontalAlignment":"left"},{"range":"B26","value":"meshtexture","fontColor":"#222222","horizontalAlignment":"left"},{"range":"C26","value":"sb:barinteriorkit/wine1bottle.babylon","fontColor":"#222222","horizontalAlignment":"left"},{"range":"J26","value":"color: 0.73,0.23,0.22","fontColor":"#ffffff","backgroundColor":"#ba3b38","horizontalAlignment":"left"},{"range":"K26","value":"wine1block","fontColor":"#222222","horizontalAlignment":"left"},{"range":"A27","value":"winemesha002","fontColor":"#222222","horizontalAlignment":"left"},{"range":"B27","value":"meshtexture","fontColor":"#222222","horizontalAlignment":"left"},{"range":"C27","value":"sb:barinteriorkit/wine1top.babylon","fontColor":"#222222","horizontalAlignment":"left"},{"range":"J27","value":"color: 0,.4,.77","fontColor":"#ffffff","backgroundColor":"#0066c4","horizontalAlignment":"left"},{"range":"K27","value":"wine1block","fontColor":"#222222","horizontalAlignment":"left"},{"range":"A28","value":"winemesha003","fontColor":"#222222","horizontalAlignment":"left"},{"range":"B28","value":"meshtexture","fontColor":"#222222","horizontalAlignment":"left"},{"range":"C28","value":"sb:barinteriorkit/wine1label.babylon","fontColor":"#222222","horizontalAlignment":"left"},{"range":"D28","value":"sb:barinteriorkit/wine1labels_D.png","fontColor":"#222222","horizontalAlignment":"left"},{"range":"G28","value":"sb:barinteriorkit/wine1labels_D.png","fontColor":"#222222","horizontalAlignment":"left"},{"range":"H28","value":4,"fontColor":"#222222","horizontalAlignment":"left"},{"range":"I28","value":"x","fontColor":"#222222","horizontalAlignment":"left"},{"range":"J28","value":"wine1material","fontColor":"#222222","horizontalAlignment":"left"},{"range":"K28","value":"wine1block","fontColor":"#222222","horizontalAlignment":"left"},{"range":"A29","value":"winemesha004","fontColor":"#222222","horizontalAlignment":"left"},{"range":"B29","value":"meshtexture","fontColor":"#222222","horizontalAlignment":"left"},{"range":"C29","value":"sb:barinteriorkit/wine1bottle.babylon","fontColor":"#222222","horizontalAlignment":"left"},{"range":"J29","value":"color: 0.3,1.33,0.53","backgroundColor":"#4dff87","horizontalAlignment":"left"},{"range":"K29","value":"wine12block","fontColor":"#222222","horizontalAlignment":"left"},{"range":"A30","value":"winemesha005","fontColor":"#222222","horizontalAlignment":"left"},{"range":"B30","value":"meshtexture","fontColor":"#222222","horizontalAlignment":"left"},{"range":"C30","value":"sb:barinteriorkit/wine1top.babylon","fontColor":"#222222","horizontalAlignment":"left"},{"range":"J30","value":"color: 1,0.13,1","backgroundColor":"#ff21ff","horizontalAlignment":"left"},{"range":"K30","value":"wine12block","fontColor":"#222222","horizontalAlignment":"left"},{"range":"A31","value":"winemesha006","fontColor":"#222222","horizontalAlignment":"left"},{"range":"B31","value":"meshtexture","fontColor":"#222222","horizontalAlignment":"left"},{"range":"C31","value":"sb:barinteriorkit/wine1label2.babylon","fontColor":"#222222","horizontalAlignment":"left"},{"range":"D31","value":"sb:barinteriorkit/wine1labels_D.png","fontColor":"#222222","horizontalAlignment":"left"},{"range":"G31","value":"sb:barinteriorkit/wine1labels_D.png","fontColor":"#222222","horizontalAlignment":"left"},{"range":"H31","value":4,"fontColor":"#222222","horizontalAlignment":"left"},{"range":"I31","value":"x","fontColor":"#222222","horizontalAlignment":"left"},{"range":"J31","value":"wine12material","fontColor":"#222222","horizontalAlignment":"left"},{"range":"K31","value":"wine12block","fontColor":"#222222","horizontalAlignment":"left"},{"range":"A32","value":"winemesha007","fontColor":"#222222","horizontalAlignment":"left"},{"range":"B32","value":"meshtexture","fontColor":"#222222","horizontalAlignment":"left"},{"range":"C32","value":"sb:barinteriorkit/wine1bottle.babylon","fontColor":"#222222","horizontalAlignment":"left"},{"range":"J32","value":"color: 2,0.5,1","backgroundColor":"#ff80ff","horizontalAlignment":"left"},{"range":"K32","value":"wine13block","fontColor":"#222222","horizontalAlignment":"left"},{"range":"A33","value":"winemesha008","fontColor":"#222222","horizontalAlignment":"left"},{"range":"B33","value":"meshtexture","fontColor":"#222222","horizontalAlignment":"left"},{"range":"C33","value":"sb:barinteriorkit/wine1top.babylon","fontColor":"#222222","horizontalAlignment":"left"},{"range":"J33","value":"color: 0.7,0.1,.2","fontColor":"#ffffff","backgroundColor":"#b31a33","horizontalAlignment":"left"},{"range":"K33","value":"wine13block","fontColor":"#222222","horizontalAlignment":"left"},{"range":"A34","value":"winemesha009","fontColor":"#222222","horizontalAlignment":"left"},{"range":"B34","value":"meshtexture","fontColor":"#222222","horizontalAlignment":"left"},{"range":"C34","value":"sb:barinteriorkit/wine1label3.babylon","fontColor":"#222222","horizontalAlignment":"left"},{"range":"D34","value":"sb:barinteriorkit/wine1labels_D.png","fontColor":"#222222","horizontalAlignment":"left"},{"range":"G34","value":"sb:barinteriorkit/wine1labels_D.png","fontColor":"#222222","horizontalAlignment":"left"},{"range":"H34","value":4,"fontColor":"#222222","horizontalAlignment":"left"},{"range":"I34","value":"x","fontColor":"#222222","horizontalAlignment":"left"},{"range":"J34","value":"wine13material","fontColor":"#222222","horizontalAlignment":"left"},{"range":"K34","value":"wine13block","fontColor":"#222222","horizontalAlignment":"left"},{"range":"A35","value":"winemesha010","fontColor":"#222222","horizontalAlignment":"left"},{"range":"B35","value":"meshtexture","fontColor":"#222222","horizontalAlignment":"left"},{"range":"C35","value":"sb:barinteriorkit/wine1bottle.babylon","fontColor":"#222222","horizontalAlignment":"left"},{"range":"J35","value":"color: 0.3,0,0.1","fontColor":"#ffffff","backgroundColor":"#4d001a","horizontalAlignment":"left"},{"range":"K35","value":"wine14block","fontColor":"#222222","horizontalAlignment":"left"},{"range":"A36","value":"winemesha011","fontColor":"#222222","horizontalAlignment":"left"},{"range":"B36","value":"meshtexture","fontColor":"#222222","horizontalAlignment":"left"},{"range":"C36","value":"sb:barinteriorkit/wine1top.babylon","fontColor":"#222222","horizontalAlignment":"left"},{"range":"J36","value":"color: 0.27,0.13,.2","fontColor":"#ffffff","backgroundColor":"#452133","horizontalAlignment":"left"},{"range":"K36","value":"wine14block","fontColor":"#222222","horizontalAlignment":"left"},{"range":"A37","value":"winemesha012","fontColor":"#222222","horizontalAlignment":"left"},{"range":"B37","value":"meshtexture","fontColor":"#222222","horizontalAlignment":"left"},{"range":"C37","value":"sb:barinteriorkit/wine1label4.babylon","fontColor":"#222222","horizontalAlignment":"left"},{"range":"D37","value":"sb:barinteriorkit/wine1labels_D.png","fontColor":"#222222","horizontalAlignment":"left"},{"range":"G37","value":"sb:barinteriorkit/wine1labels_D.png","fontColor":"#222222","horizontalAlignment":"left"},{"range":"H37","value":4,"fontColor":"#222222","horizontalAlignment":"left"},{"range":"I37","value":"x","fontColor":"#222222","horizontalAlignment":"left"},{"range":"J37","value":"wine14block","fontColor":"#222222","horizontalAlignment":"left"},{"range":"K37","value":"wine14block","fontColor":"#222222","horizontalAlignment":"left"},{"range":"A38","value":"winemesha013","fontColor":"#222222","horizontalAlignment":"left"},{"range":"B38","value":"meshtexture","fontColor":"#222222","horizontalAlignment":"left"},{"range":"C38","value":"sb:barinteriorkit/wine2bottle.babylon","fontColor":"#222222","horizontalAlignment":"left"},{"range":"J38","value":"color: 0.73,0.23,1","backgroundColor":"#ba3bff","horizontalAlignment":"left"},{"range":"K38","value":"wine2block","fontColor":"#222222","horizontalAlignment":"left"},{"range":"A39","value":"winemesha014","fontColor":"#222222","horizontalAlignment":"left"},{"range":"B39","value":"meshtexture","fontColor":"#222222","horizontalAlignment":"left"},{"range":"C39","value":"sb:barinteriorkit/wine2top.babylon","fontColor":"#222222","horizontalAlignment":"left"},{"range":"J39","value":"color: 0.2,0.3,0.13","fontColor":"#ffffff","backgroundColor":"#334d21","horizontalAlignment":"left"},{"range":"K39","value":"wine2block","fontColor":"#222222","horizontalAlignment":"left"},{"range":"A40","value":"winemesha015","fontColor":"#222222","horizontalAlignment":"left"},{"range":"B40","value":"meshtexture","fontColor":"#222222","horizontalAlignment":"left"},{"range":"C40","value":"sb:barinteriorkit/wine2label.babylon","fontColor":"#222222","horizontalAlignment":"left"},{"range":"D40","value":"sb:barinteriorkit/wine2labels_D.png","fontColor":"#222222","horizontalAlignment":"left"},{"range":"G40","value":"sb:barinteriorkit/wine2labels_D.png","fontColor":"#222222","horizontalAlignment":"left"},{"range":"H40","value":4,"fontColor":"#222222","horizontalAlignment":"left"},{"range":"I40","value":"x","fontColor":"#222222","horizontalAlignment":"left"},{"range":"J40","value":"wine2block","fontColor":"#222222","horizontalAlignment":"left"},{"range":"K40","value":"wine2block","fontColor":"#222222","horizontalAlignment":"left"},{"range":"A41","value":"winemesha016","fontColor":"#222222","horizontalAlignment":"left"},{"range":"B41","value":"meshtexture","fontColor":"#222222","horizontalAlignment":"left"},{"range":"C41","value":"sb:barinteriorkit/wine2bottle.babylon","fontColor":"#222222","horizontalAlignment":"left"},{"range":"J41","value":"color: 0.3,0.73,0.3","fontColor":"#ffffff","backgroundColor":"#4dba4d","horizontalAlignment":"left"},{"range":"K41","value":"wineblock22","fontColor":"#222222","horizontalAlignment":"left"},{"range":"A42","value":"winemesha017","fontColor":"#222222","horizontalAlignment":"left"},{"range":"B42","value":"meshtexture","fontColor":"#222222","horizontalAlignment":"left"},{"range":"C42","value":"sb:barinteriorkit/wine2top.babylon","fontColor":"#222222","horizontalAlignment":"left"},{"range":"J42","value":"color: 0.27,0.3,.2","fontColor":"#ffffff","backgroundColor":"#454d33","horizontalAlignment":"left"},{"range":"K42","value":"wineblock22","fontColor":"#222222","horizontalAlignment":"left"},{"range":"A43","value":"winemesha018","fontColor":"#222222","horizontalAlignment":"left"},{"range":"B43","value":"meshtexture","fontColor":"#222222","horizontalAlignment":"left"},{"range":"C43","value":"sb:barinteriorkit/wine2label2.babylon","fontColor":"#222222","horizontalAlignment":"left"},{"range":"D43","value":"sb:barinteriorkit/wine2labels_D.png","fontColor":"#222222","horizontalAlignment":"left"},{"range":"G43","value":"sb:barinteriorkit/wine2labels_D.png","fontColor":"#222222","horizontalAlignment":"left"},{"range":"H43","value":4,"fontColor":"#222222","horizontalAlignment":"left"},{"range":"I43","value":"x","fontColor":"#222222","horizontalAlignment":"left"},{"range":"J43","value":"wineblock22","fontColor":"#222222","horizontalAlignment":"left"},{"range":"K43","value":"wineblock22","fontColor":"#222222","horizontalAlignment":"left"},{"range":"A44","value":"winemesha019","fontColor":"#222222","horizontalAlignment":"left"},{"range":"B44","value":"meshtexture","fontColor":"#222222","horizontalAlignment":"left"},{"range":"C44","value":"sb:barinteriorkit/wine2bottle.babylon","fontColor":"#222222","horizontalAlignment":"left"},{"range":"J44","value":"color: 0.3,1,1","backgroundColor":"#4dffff","horizontalAlignment":"left"},{"range":"K44","value":"wineblock23","fontColor":"#222222","horizontalAlignment":"left"},{"range":"A45","value":"winemesha020","fontColor":"#222222","horizontalAlignment":"left"},{"range":"B45","value":"meshtexture","fontColor":"#222222","horizontalAlignment":"left"},{"range":"C45","value":"sb:barinteriorkit/wine2top.babylon","fontColor":"#222222","horizontalAlignment":"left"},{"range":"J45","value":"color: 0.7,0.3,1","backgroundColor":"#b34dff","horizontalAlignment":"left"},{"range":"K45","value":"wineblock23","fontColor":"#222222","horizontalAlignment":"left"},{"range":"A46","value":"winemesha021","fontColor":"#222222","horizontalAlignment":"left"},{"range":"B46","value":"meshtexture","fontColor":"#222222","horizontalAlignment":"left"},{"range":"C46","value":"sb:barinteriorkit/wine2label3.babylon","fontColor":"#222222","horizontalAlignment":"left"},{"range":"D46","value":"sb:barinteriorkit/wine2labels_D.png","fontColor":"#222222","horizontalAlignment":"left"},{"range":"G46","value":"sb:barinteriorkit/wine2labels_D.png","fontColor":"#222222","horizontalAlignment":"left"},{"range":"H46","value":4,"fontColor":"#222222","horizontalAlignment":"left"},{"range":"I46","value":"x","fontColor":"#222222","horizontalAlignment":"left"},{"range":"J46","value":"wineblock23","fontColor":"#222222","horizontalAlignment":"left"},{"range":"K46","value":"wineblock23","fontColor":"#222222","horizontalAlignment":"left"},{"range":"A47","value":"winemesha022","fontColor":"#222222","horizontalAlignment":"left"},{"range":"B47","value":"meshtexture","fontColor":"#222222","horizontalAlignment":"left"},{"range":"C47","value":"sb:barinteriorkit/wine2bottle.babylon","fontColor":"#222222","horizontalAlignment":"left"},{"range":"J47","value":"color: 0.5,0.3,0","fontColor":"#ffffff","backgroundColor":"#804d00","horizontalAlignment":"left"},{"range":"K47","value":"wineblock24","fontColor":"#222222","horizontalAlignment":"left"},{"range":"A48","value":"winemesha023","fontColor":"#222222","horizontalAlignment":"left"},{"range":"B48","value":"meshtexture","fontColor":"#222222","horizontalAlignment":"left"},{"range":"C48","value":"sb:barinteriorkit/wine2top.babylon","fontColor":"#222222","horizontalAlignment":"left"},{"range":"J48","value":"color: 0.27,0,.8","fontColor":"#ffffff","backgroundColor":"#4500cc","horizontalAlignment":"left"},{"range":"K48","value":"wineblock24","fontColor":"#222222","horizontalAlignment":"left"},{"range":"A49","value":"winemesha024","fontColor":"#222222","horizontalAlignment":"left"},{"range":"B49","value":"meshtexture","fontColor":"#222222","horizontalAlignment":"left"},{"range":"C49","value":"sb:barinteriorkit/wine2label4.babylon","fontColor":"#222222","horizontalAlignment":"left"},{"range":"D49","value":"sb:barinteriorkit/wine2labels_D.png","fontColor":"#222222","horizontalAlignment":"left"},{"range":"G49","value":"sb:barinteriorkit/wine2labels_D.png","fontColor":"#222222","horizontalAlignment":"left"},{"range":"H49","value":4,"fontColor":"#222222","horizontalAlignment":"left"},{"range":"I49","value":"x","fontColor":"#222222","horizontalAlignment":"left"},{"range":"J49","value":"wineblock24","fontColor":"#222222","horizontalAlignment":"left"},{"range":"K49","value":"wineblock24","fontColor":"#222222","horizontalAlignment":"left"},{"range":"A50","value":"winemesha025","fontColor":"#222222","horizontalAlignment":"left"},{"range":"B50","value":"meshtexture","fontColor":"#222222","horizontalAlignment":"left"},{"range":"C50","value":"sb:barinteriorkit/wine4bottle.babylon","fontColor":"#222222","horizontalAlignment":"left"},{"range":"J50","value":"color: 0.3,0.3,0.5","fontColor":"#ffffff","backgroundColor":"#4d4d80","horizontalAlignment":"left"},{"range":"K50","value":"wineblock4","fontColor":"#222222","horizontalAlignment":"left"},{"range":"A51","value":"winemesha026","fontColor":"#222222","horizontalAlignment":"left"},{"range":"B51","value":"meshtexture","fontColor":"#222222","horizontalAlignment":"left"},{"range":"C51","value":"sb:barinteriorkit/wine4top.babylon","fontColor":"#222222","horizontalAlignment":"left"},{"range":"J51","value":"color: 0.27,0,1","fontColor":"#ffffff","backgroundColor":"#4500ff","horizontalAlignment":"left"},{"range":"K51","value":"wineblock4","fontColor":"#222222","horizontalAlignment":"left"},{"range":"A52","value":"winemesha027","fontColor":"#222222","horizontalAlignment":"left"},{"range":"B52","value":"meshtexture","fontColor":"#222222","horizontalAlignment":"left"},{"range":"C52","value":"sb:barinteriorkit/wine4label.babylon","fontColor":"#222222","horizontalAlignment":"left"},{"range":"D52","value":"sb:barinteriorkit/wine4labels_D.png","fontColor":"#222222","horizontalAlignment":"left"},{"range":"G52","value":"sb:barinteriorkit/wine4labels_D.png","fontColor":"#222222","horizontalAlignment":"left"},{"range":"H52","value":4,"fontColor":"#222222","horizontalAlignment":"left"},{"range":"I52","value":"x","fontColor":"#222222","horizontalAlignment":"left"},{"range":"J52","value":"wineblock4","fontColor":"#222222","horizontalAlignment":"left"},{"range":"K52","value":"wineblock4","fontColor":"#222222","horizontalAlignment":"left"},{"range":"A53","value":"winemesha028","fontColor":"#222222","horizontalAlignment":"left"},{"range":"B53","value":"meshtexture","fontColor":"#222222","horizontalAlignment":"left"},{"range":"C53","value":"sb:barinteriorkit/wine4bottle.babylon","fontColor":"#222222","horizontalAlignment":"left"},{"range":"J53","value":"color: 1,0.73,0.53","backgroundColor":"#ffba87","horizontalAlignment":"left"},{"range":"K53","value":"wineblock42","fontColor":"#222222","horizontalAlignment":"left"},{"range":"A54","value":"winemesha029","fontColor":"#222222","horizontalAlignment":"left"},{"range":"B54","value":"meshtexture","fontColor":"#222222","horizontalAlignment":"left"},{"range":"C54","value":"sb:barinteriorkit/wine4top.babylon","fontColor":"#222222","horizontalAlignment":"left"},{"range":"J54","value":"color: 0.27,0.13,2","backgroundColor":"#4521ff","horizontalAlignment":"left"},{"range":"K54","value":"wineblock42","fontColor":"#222222","horizontalAlignment":"left"},{"range":"A55","value":"winemesha030","fontColor":"#222222","horizontalAlignment":"left"},{"range":"B55","value":"meshtexture","fontColor":"#222222","horizontalAlignment":"left"},{"range":"C55","value":"sb:barinteriorkit/wine4label2.babylon","fontColor":"#222222","horizontalAlignment":"left"},{"range":"D55","value":"sb:barinteriorkit/wine4labels_D.png","fontColor":"#222222","horizontalAlignment":"left"},{"range":"G55","value":"sb:barinteriorkit/wine4labels_D.png","fontColor":"#222222","horizontalAlignment":"left"},{"range":"H55","value":4,"fontColor":"#222222","horizontalAlignment":"left"},{"range":"I55","value":"x","fontColor":"#222222","horizontalAlignment":"left"},{"range":"J55","value":"wineblock42","fontColor":"#222222","horizontalAlignment":"left"},{"range":"K55","value":"wineblock42","fontColor":"#222222","horizontalAlignment":"left"},{"range":"A56","value":"winemesha031","fontColor":"#222222","horizontalAlignment":"left"},{"range":"B56","value":"meshtexture","fontColor":"#222222","horizontalAlignment":"left"},{"range":"C56","value":"sb:barinteriorkit/wine4bottle.babylon","fontColor":"#222222","horizontalAlignment":"left"},{"range":"J56","value":"color: 0.3,2,2","backgroundColor":"#4dffff","horizontalAlignment":"left"},{"range":"K56","value":"wineblock43","fontColor":"#222222","horizontalAlignment":"left"},{"range":"A57","value":"winemesha032","fontColor":"#222222","horizontalAlignment":"left"},{"range":"B57","value":"meshtexture","fontColor":"#222222","horizontalAlignment":"left"},{"range":"C57","value":"sb:barinteriorkit/wine4top.babylon","fontColor":"#222222","horizontalAlignment":"left"},{"range":"J57","value":"color: 0.27,0.13,0","fontColor":"#ffffff","backgroundColor":"#452100","horizontalAlignment":"left"},{"range":"K57","value":"wineblock43","fontColor":"#222222","horizontalAlignment":"left"},{"range":"A58","value":"winemesha033","fontColor":"#222222","horizontalAlignment":"left"},{"range":"B58","value":"meshtexture","fontColor":"#222222","horizontalAlignment":"left"},{"range":"C58","value":"sb:barinteriorkit/wine4label3.babylon","fontColor":"#222222","horizontalAlignment":"left"},{"range":"D58","value":"sb:barinteriorkit/wine4labels_D.png","fontColor":"#222222","horizontalAlignment":"left"},{"range":"G58","value":"sb:barinteriorkit/wine4labels_D.png","fontColor":"#222222","horizontalAlignment":"left"},{"range":"H58","value":4,"fontColor":"#222222","horizontalAlignment":"left"},{"range":"I58","value":"x","fontColor":"#222222","horizontalAlignment":"left"},{"range":"J58","value":"wineblock43","fontColor":"#222222","horizontalAlignment":"left"},{"range":"K58","value":"wineblock43","fontColor":"#222222","horizontalAlignment":"left"},{"range":"A59","value":"winemesha034","fontColor":"#222222","horizontalAlignment":"left"},{"range":"B59","value":"meshtexture","fontColor":"#222222","horizontalAlignment":"left"},{"range":"C59","value":"sb:barinteriorkit/wine4bottle.babylon","fontColor":"#222222","horizontalAlignment":"left"},{"range":"J59","value":"color: 0,0.3,0.5","fontColor":"#ffffff","backgroundColor":"#004d80","horizontalAlignment":"left"},{"range":"K59","value":"wineblock44","fontColor":"#222222","horizontalAlignment":"left"},{"range":"A60","value":"winemesha035","fontColor":"#222222","horizontalAlignment":"left"},{"range":"B60","value":"meshtexture","fontColor":"#222222","horizontalAlignment":"left"},{"range":"C60","value":"sb:barinteriorkit/wine4top.babylon","fontColor":"#222222","horizontalAlignment":"left"},{"range":"J60","value":"color: 0.27,2,0","backgroundColor":"#45ff00","horizontalAlignment":"left"},{"range":"K60","value":"wineblock44","fontColor":"#222222","horizontalAlignment":"left"},{"range":"A61","value":"winemesha036","fontColor":"#222222","horizontalAlignment":"left"},{"range":"B61","value":"meshtexture","fontColor":"#222222","horizontalAlignment":"left"},{"range":"C61","value":"sb:barinteriorkit/wine4label4.babylon","fontColor":"#222222","horizontalAlignment":"left"},{"range":"D61","value":"sb:barinteriorkit/wine4labels_D.png","fontColor":"#222222","horizontalAlignment":"left"},{"range":"G61","value":"sb:barinteriorkit/wine4labels_D.png","fontColor":"#222222","horizontalAlignment":"left"},{"range":"H61","value":4,"fontColor":"#222222","horizontalAlignment":"left"},{"range":"I61","value":"x","fontColor":"#222222","horizontalAlignment":"left"},{"range":"J61","value":"wineblock44","fontColor":"#222222","horizontalAlignment":"left"},{"range":"K61","value":"wineblock44","fontColor":"#222222","horizontalAlignment":"left"},{"range":"A62","value":"winemesha037","fontColor":"#222222","horizontalAlignment":"left"},{"range":"B62","value":"meshtexture","fontColor":"#222222","horizontalAlignment":"left"},{"range":"C62","value":"sb:barinteriorkit/wine5bottle.babylon","fontColor":"#222222","horizontalAlignment":"left"},{"range":"J62","value":"color: 0.1,0.73,0.53","fontColor":"#ffffff","backgroundColor":"#1aba87","horizontalAlignment":"left"},{"range":"K62","value":"wineblock5","fontColor":"#222222","horizontalAlignment":"left"},{"range":"A63","value":"winemesha038","fontColor":"#222222","horizontalAlignment":"left"},{"range":"B63","value":"meshtexture","fontColor":"#222222","horizontalAlignment":"left"},{"range":"C63","value":"sb:barinteriorkit/wine5top.babylon","fontColor":"#222222","horizontalAlignment":"left"},{"range":"J63","value":"color: 0.27,0.13,2","backgroundColor":"#4521ff","horizontalAlignment":"left"},{"range":"K63","value":"wineblock5","fontColor":"#222222","horizontalAlignment":"left"},{"range":"A64","value":"winemesha039","fontColor":"#222222","horizontalAlignment":"left"},{"range":"B64","value":"meshtexture","fontColor":"#222222","horizontalAlignment":"left"},{"range":"C64","value":"sb:barinteriorkit/wine5label.babylon","fontColor":"#222222","horizontalAlignment":"left"},{"range":"D64","value":"sb:barinteriorkit/wine5labels_D.png","fontColor":"#222222","horizontalAlignment":"left"},{"range":"G64","value":"sb:barinteriorkit/wine5labels_D.png","fontColor":"#222222","horizontalAlignment":"left"},{"range":"H64","value":4,"fontColor":"#222222","horizontalAlignment":"left"},{"range":"I64","value":"x","fontColor":"#222222","horizontalAlignment":"left"},{"range":"J64","value":"wineblock5","fontColor":"#222222","horizontalAlignment":"left"},{"range":"K64","value":"wineblock5","fontColor":"#222222","horizontalAlignment":"left"},{"range":"A65","value":"winemesha040","fontColor":"#222222","horizontalAlignment":"left"},{"range":"B65","value":"meshtexture","fontColor":"#222222","horizontalAlignment":"left"},{"range":"C65","value":"sb:barinteriorkit/wine5bottle.babylon","fontColor":"#222222","horizontalAlignment":"left"},{"range":"J65","value":"color: 0.3,0.3,0.53","fontColor":"#ffffff","backgroundColor":"#4d4d87","horizontalAlignment":"left"},{"range":"K65","value":"wineblock52","fontColor":"#222222","horizontalAlignment":"left"},{"range":"A66","value":"winemesha041","fontColor":"#222222","horizontalAlignment":"left"},{"range":"B66","value":"meshtexture","fontColor":"#222222","horizontalAlignment":"left"},{"range":"C66","value":"sb:barinteriorkit/wine5top.babylon","fontColor":"#222222","horizontalAlignment":"left"},{"range":"J66","value":"color: 0.27,1,1","fontColor":"#ffffff","backgroundColor":"#451aff","horizontalAlignment":"left"},{"range":"K66","value":"wineblock52","fontColor":"#222222","horizontalAlignment":"left"},{"range":"A67","value":"winemesha042","fontColor":"#222222","horizontalAlignment":"left"},{"range":"B67","value":"meshtexture","fontColor":"#222222","horizontalAlignment":"left"},{"range":"C67","value":"sb:barinteriorkit/wine5label2.babylon","fontColor":"#222222","horizontalAlignment":"left"},{"range":"D67","value":"sb:barinteriorkit/wine5labels_D.png","fontColor":"#222222","horizontalAlignment":"left"},{"range":"G67","value":"sb:barinteriorkit/wine5labels_D.png","fontColor":"#222222","horizontalAlignment":"left"},{"range":"H67","value":4,"fontColor":"#222222","horizontalAlignment":"left"},{"range":"I67","value":"x","fontColor":"#222222","horizontalAlignment":"left"},{"range":"J67","value":"wineblock52","fontColor":"#222222","horizontalAlignment":"left"},{"range":"K67","value":"wineblock52","fontColor":"#222222","horizontalAlignment":"left"},{"range":"A68","value":"winemesha043","fontColor":"#222222","horizontalAlignment":"left"},{"range":"B68","value":"meshtexture","fontColor":"#222222","horizontalAlignment":"left"},{"range":"C68","value":"sb:barinteriorkit/wine5bottle.babylon","fontColor":"#222222","horizontalAlignment":"left"},{"range":"J68","value":"color: 3,0.73,0.53","backgroundColor":"#ffba87","horizontalAlignment":"left"},{"range":"K68","value":"wineblock53","fontColor":"#222222","horizontalAlignment":"left"},{"range":"A69","value":"winemesha044","fontColor":"#222222","horizontalAlignment":"left"},{"range":"B69","value":"meshtexture","fontColor":"#222222","horizontalAlignment":"left"},{"range":"C69","value":"sb:barinteriorkit/wine5top.babylon","fontColor":"#222222","horizontalAlignment":"left"},{"range":"J69","value":"color: 0.7,0.3,1","backgroundColor":"#b34dff","horizontalAlignment":"left"},{"range":"K69","value":"wineblock53","fontColor":"#222222","horizontalAlignment":"left"},{"range":"A70","value":"winemesha045","fontColor":"#222222","horizontalAlignment":"left"},{"range":"B70","value":"meshtexture","fontColor":"#222222","horizontalAlignment":"left"},{"range":"C70","value":"sb:barinteriorkit/wine5label3.babylon","fontColor":"#222222","horizontalAlignment":"left"},{"range":"D70","value":"sb:barinteriorkit/wine5labels_D.png","fontColor":"#222222","horizontalAlignment":"left"},{"range":"G70","value":"sb:barinteriorkit/wine5labels_D.png","fontColor":"#222222","horizontalAlignment":"left"},{"range":"H70","value":4,"fontColor":"#222222","horizontalAlignment":"left"},{"range":"I70","value":"x","fontColor":"#222222","horizontalAlignment":"left"},{"range":"J70","value":"wineblock53","fontColor":"#222222","horizontalAlignment":"left"},{"range":"K70","value":"wineblock53","fontColor":"#222222","horizontalAlignment":"left"},{"range":"A71","value":"winemesha046","fontColor":"#222222","horizontalAlignment":"left"},{"range":"B71","value":"meshtexture","fontColor":"#222222","horizontalAlignment":"left"},{"range":"C71","value":"sb:barinteriorkit/wine7bottle.babylon","fontColor":"#222222","horizontalAlignment":"left"},{"range":"J71","value":"color: 0.3,0.7,0.5","backgroundColor":"#4db380","horizontalAlignment":"left"},{"range":"K71","value":"wineblock7","fontColor":"#222222","horizontalAlignment":"left"},{"range":"A72","value":"winemesha047","fontColor":"#222222","horizontalAlignment":"left"},{"range":"B72","value":"meshtexture","fontColor":"#222222","horizontalAlignment":"left"},{"range":"C72","value":"sb:barinteriorkit/wine7top.babylon","fontColor":"#222222","horizontalAlignment":"left"},{"range":"J72","value":"color: 0.27,1,1","backgroundColor":"#45ffff","horizontalAlignment":"left"},{"range":"K72","value":"wineblock7","fontColor":"#222222","horizontalAlignment":"left"},{"range":"A73","value":"winemesha048","fontColor":"#222222","horizontalAlignment":"left"},{"range":"B73","value":"meshtexture","fontColor":"#222222","horizontalAlignment":"left"},{"range":"C73","value":"sb:barinteriorkit/wine7label.babylon","fontColor":"#222222","horizontalAlignment":"left"},{"range":"D73","value":"sb:barinteriorkit/wine7labels_D.png","fontColor":"#222222","horizontalAlignment":"left"},{"range":"G73","value":"sb:barinteriorkit/wine7labels_D.png","fontColor":"#222222","horizontalAlignment":"left"},{"range":"H73","value":4,"fontColor":"#222222","horizontalAlignment":"left"},{"range":"I73","value":"x","fontColor":"#222222","horizontalAlignment":"left"},{"range":"J73","value":"wineblock7","fontColor":"#222222","horizontalAlignment":"left"},{"range":"K73","value":"wineblock7","fontColor":"#222222","horizontalAlignment":"left"},{"range":"A74","value":"winemesha049","fontColor":"#222222","horizontalAlignment":"left"},{"range":"B74","value":"meshtexture","fontColor":"#222222","horizontalAlignment":"left"},{"range":"C74","value":"sb:barinteriorkit/wine7bottle.babylon","fontColor":"#222222","horizontalAlignment":"left"},{"range":"J74","value":"color: 1,0,0.53","backgroundColor":"#ff0087","horizontalAlignment":"left"},{"range":"K74","value":"wineblock72","fontColor":"#222222","horizontalAlignment":"left"},{"range":"A75","value":"winemesha050","fontColor":"#222222","horizontalAlignment":"left"},{"range":"B75","value":"meshtexture","fontColor":"#222222","horizontalAlignment":"left"},{"range":"C75","value":"sb:barinteriorkit/wine7top.babylon","fontColor":"#222222","horizontalAlignment":"left"},{"range":"J75","value":"color: 0.2,1,1","backgroundColor":"#33ffff","horizontalAlignment":"left"},{"range":"K75","value":"wineblock72","fontColor":"#222222","horizontalAlignment":"left"},{"range":"A76","value":"winemesha051","fontColor":"#222222","horizontalAlignment":"left"},{"range":"B76","value":"meshtexture","fontColor":"#222222","horizontalAlignment":"left"},{"range":"C76","value":"sb:barinteriorkit/wine7label2.babylon","fontColor":"#222222","horizontalAlignment":"left"},{"range":"D76","value":"sb:barinteriorkit/wine7labels_D.png","fontColor":"#222222","horizontalAlignment":"left"},{"range":"G76","value":"sb:barinteriorkit/wine7labels_D.png","fontColor":"#222222","horizontalAlignment":"left"},{"range":"H76","value":4,"fontColor":"#222222","horizontalAlignment":"left"},{"range":"I76","value":"x","fontColor":"#222222","horizontalAlignment":"left"},{"range":"J76","value":"wineblock72","fontColor":"#222222","horizontalAlignment":"left"},{"range":"K76","value":"wineblock72","fontColor":"#222222","horizontalAlignment":"left"},{"range":"A77","value":"winemesha052","fontColor":"#222222","horizontalAlignment":"left"},{"range":"B77","value":"meshtexture","fontColor":"#222222","horizontalAlignment":"left"},{"range":"C77","value":"sb:barinteriorkit/wine7bottle.babylon","fontColor":"#222222","horizontalAlignment":"left"},{"range":"J77","value":"color: 0.3,1,0","fontColor":"#ffffff","backgroundColor":"#4dff00","horizontalAlignment":"left"},{"range":"K77","value":"wineblock73","fontColor":"#222222","horizontalAlignment":"left"},{"range":"A78","value":"winemesha053","fontColor":"#222222","horizontalAlignment":"left"},{"range":"B78","value":"meshtexture","fontColor":"#222222","horizontalAlignment":"left"},{"range":"C78","value":"sb:barinteriorkit/wine7top.babylon","fontColor":"#222222","horizontalAlignment":"left"},{"range":"J78","value":"color: 1,0,1","backgroundColor":"#ff00ff","horizontalAlignment":"left"},{"range":"K78","value":"wineblock73","fontColor":"#222222","horizontalAlignment":"left"},{"range":"A79","value":"winemesha054","fontColor":"#222222","horizontalAlignment":"left"},{"range":"B79","value":"meshtexture","fontColor":"#222222","horizontalAlignment":"left"},{"range":"C79","value":"sb:barinteriorkit/wine7label3.babylon","fontColor":"#222222","horizontalAlignment":"left"},{"range":"D79","value":"sb:barinteriorkit/wine7labels_D.png","fontColor":"#222222","horizontalAlignment":"left"},{"range":"G79","value":"sb:barinteriorkit/wine7labels_D.png","fontColor":"#222222","horizontalAlignment":"left"},{"range":"H79","value":4,"fontColor":"#222222","horizontalAlignment":"left"},{"range":"I79","value":"x","fontColor":"#222222","horizontalAlignment":"left"},{"range":"J79","value":"wineblock73","fontColor":"#222222","horizontalAlignment":"left"},{"range":"K79","value":"wineblock73","fontColor":"#222222","horizontalAlignment":"left"},{"range":"A80","value":"winemesha055","fontColor":"#222222","horizontalAlignment":"left"},{"range":"B80","value":"meshtexture","fontColor":"#222222","horizontalAlignment":"left"},{"range":"C80","value":"sb:barinteriorkit/wine7bottle.babylon","fontColor":"#222222","horizontalAlignment":"left"},{"range":"J80","value":"color: 0.3,0.5,0","fontColor":"#ffffff","backgroundColor":"#4d8000","horizontalAlignment":"left"},{"range":"K80","value":"wineblock74","fontColor":"#222222","horizontalAlignment":"left"},{"range":"A81","value":"winemesha056","fontColor":"#222222","horizontalAlignment":"left"},{"range":"B81","value":"meshtexture","fontColor":"#222222","horizontalAlignment":"left"},{"range":"C81","value":"sb:barinteriorkit/wine7top.babylon","fontColor":"#222222","horizontalAlignment":"left"},{"range":"J81","value":"color: 0.27,0,1","fontColor":"#ffffff","backgroundColor":"#4500ff","horizontalAlignment":"left"},{"range":"K81","value":"wineblock74","fontColor":"#222222","horizontalAlignment":"left"},{"range":"A82","value":"winemesha057","fontColor":"#222222","horizontalAlignment":"left"},{"range":"B82","value":"meshtexture","fontColor":"#222222","horizontalAlignment":"left"},{"range":"C82","value":"sb:barinteriorkit/wine7label4.babylon","fontColor":"#222222","horizontalAlignment":"left"},{"range":"D82","value":"sb:barinteriorkit/wine7labels_D.png","fontColor":"#222222","horizontalAlignment":"left"},{"range":"G82","value":"sb:barinteriorkit/wine7labels_D.png","fontColor":"#222222","horizontalAlignment":"left"},{"range":"H82","value":4,"fontColor":"#222222","horizontalAlignment":"left"},{"range":"I82","value":"x","fontColor":"#222222","horizontalAlignment":"left"},{"range":"J82","value":"wineblock74","fontColor":"#222222","horizontalAlignment":"left"},{"range":"K82","value":"wineblock74","fontColor":"#222222","horizontalAlignment":"left"},{"range":"A87","value":"childname","fontWeight":"bold"},{"range":"B87","value":"asset","fontWeight":"bold"},{"range":"C87","value":"childtype","fontWeight":"bold"},{"range":"D87","value":"parent","fontWeight":"bold"},{"range":"E87","value":"x","fontWeight":"bold"},{"range":"F87","value":"y","fontWeight":"bold"},{"range":"G87","value":"z","fontWeight":"bold"},{"range":"H87","value":"rx","fontWeight":"bold"},{"range":"I87","value":"ry","fontWeight":"bold"},{"range":"J87","value":"rz","fontWeight":"bold"},{"range":"K87","value":"sx","fontWeight":"bold"},{"range":"L87","value":"sy","fontWeight":"bold"},{"range":"M87","value":"sz","fontWeight":"bold"},{"range":"A88","value":"smallbarblock"},{"range":"B88","value":"blockchild"},{"range":"C88","value":"block"},{"range":"D88","value":"::scene::"},{"range":"E88","value":0,"horizontalAlignment":"general-right"},{"range":"F88","value":0,"horizontalAlignment":"general-right"},{"range":"G88","value":0,"horizontalAlignment":"general-right"},{"range":"A89","value":"wine1block"},{"range":"B89","value":"blockchild"},{"range":"C89","value":"block"},{"range":"D89","value":"::scene::"},{"range":"E89","value":0,"horizontalAlignment":"general-right"},{"range":"F89","value":5,"horizontalAlignment":"general-right"},{"range":"G89","value":0,"horizontalAlignment":"general-right"},{"range":"H89","value":"-90deg"},{"range":"I89","value":"-90deg"},{"range":"K89","value":0.1,"horizontalAlignment":"general-right"},{"range":"L89","value":0.1,"horizontalAlignment":"general-right"},{"range":"M89","value":0.1,"horizontalAlignment":"general-right"},{"range":"A90","value":"wine12block"},{"range":"B90","value":"blockchild"},{"range":"C90","value":"block"},{"range":"D90","value":"::scene::"},{"range":"E90","value":0,"horizontalAlignment":"general-right"},{"range":"F90","value":5,"horizontalAlignment":"general-right"},{"range":"G90","value":2,"horizontalAlignment":"general-right"},{"range":"H90","value":"-90deg"},{"range":"I90","value":"-90deg"},{"range":"K90","value":0.1,"horizontalAlignment":"general-right"},{"range":"L90","value":0.1,"horizontalAlignment":"general-right"},{"range":"M90","value":0.1,"horizontalAlignment":"general-right"},{"range":"A91","value":"wine13block"},{"range":"B91","value":"blockchild"},{"range":"C91","value":"block"},{"range":"D91","value":"::scene::"},{"range":"E91","value":0,"horizontalAlignment":"general-right"},{"range":"F91","value":5,"horizontalAlignment":"general-right"},{"range":"G91","value":4,"horizontalAlignment":"general-right"},{"range":"H91","value":"-90deg"},{"range":"I91","value":"-90deg"},{"range":"K91","value":0.1,"horizontalAlignment":"general-right"},{"range":"L91","value":0.1,"horizontalAlignment":"general-right"},{"range":"M91","value":0.1,"horizontalAlignment":"general-right"},{"range":"A92","value":"wine14block"},{"range":"B92","value":"blockchild"},{"range":"C92","value":"block"},{"range":"D92","value":"::scene::"},{"range":"E92","value":0,"horizontalAlignment":"general-right"},{"range":"F92","value":5,"horizontalAlignment":"general-right"},{"range":"G92","value":6,"horizontalAlignment":"general-right"},{"range":"H92","value":"-90deg"},{"range":"I92","value":"-90deg"},{"range":"K92","value":0.1,"horizontalAlignment":"general-right"},{"range":"L92","value":0.1,"horizontalAlignment":"general-right"},{"range":"M92","value":0.1,"horizontalAlignment":"general-right"},{"range":"A93","value":"wine2block"},{"range":"B93","value":"blockchild"},{"range":"C93","value":"block"},{"range":"D93","value":"::scene::"},{"range":"E93","value":0,"horizontalAlignment":"general-right"},{"range":"F93","value":5,"horizontalAlignment":"general-right"},{"range":"G93","value":-3,"horizontalAlignment":"general-right"},{"range":"H93","value":"-90deg"},{"range":"I93","value":"-90deg"},{"range":"K93","value":0.1,"horizontalAlignment":"general-right"},{"range":"L93","value":0.1,"horizontalAlignment":"general-right"},{"range":"M93","value":0.1,"horizontalAlignment":"general-right"},{"range":"A94","value":"wineblock22"},{"range":"B94","value":"blockchild"},{"range":"C94","value":"block"},{"range":"D94","value":"::scene::"},{"range":"E94","value":0,"horizontalAlignment":"general-right"},{"range":"F94","value":5,"horizontalAlignment":"general-right"},{"range":"G94","value":-5,"horizontalAlignment":"general-right"},{"range":"H94","value":"-90deg"},{"range":"I94","value":"-90deg"},{"range":"K94","value":0.1,"horizontalAlignment":"general-right"},{"range":"L94","value":0.1,"horizontalAlignment":"general-right"},{"range":"M94","value":0.1,"horizontalAlignment":"general-right"},{"range":"A95","value":"wineblock23"},{"range":"B95","value":"blockchild"},{"range":"C95","value":"block"},{"range":"D95","value":"::scene::"},{"range":"E95","value":0,"horizontalAlignment":"general-right"},{"range":"F95","value":5,"horizontalAlignment":"general-right"},{"range":"G95","value":-7,"horizontalAlignment":"general-right"},{"range":"H95","value":"-90deg"},{"range":"I95","value":"-90deg"},{"range":"K95","value":0.1,"horizontalAlignment":"general-right"},{"range":"L95","value":0.1,"horizontalAlignment":"general-right"},{"range":"M95","value":0.1,"horizontalAlignment":"general-right"},{"range":"A96","value":"wineblock24"},{"range":"B96","value":"blockchild"},{"range":"C96","value":"block"},{"range":"D96","value":"::scene::"},{"range":"E96","value":0,"horizontalAlignment":"general-right"},{"range":"F96","value":5,"horizontalAlignment":"general-right"},{"range":"G96","value":-9,"horizontalAlignment":"general-right"},{"range":"H96","value":"-90deg"},{"range":"I96","value":"-90deg"},{"range":"K96","value":0.1,"horizontalAlignment":"general-right"},{"range":"L96","value":0.1,"horizontalAlignment":"general-right"},{"range":"M96","value":0.1,"horizontalAlignment":"general-right"},{"range":"A97","value":"wineblock4"},{"range":"B97","value":"blockchild"},{"range":"C97","value":"block"},{"range":"D97","value":"::scene::"},{"range":"E97","value":0,"horizontalAlignment":"general-right"},{"range":"F97","value":5,"horizontalAlignment":"general-right"},{"range":"G97","value":-14,"horizontalAlignment":"general-right"},{"range":"H97","value":"-90deg"},{"range":"I97","value":"-90deg"},{"range":"K97","value":0.1,"horizontalAlignment":"general-right"},{"range":"L97","value":0.1,"horizontalAlignment":"general-right"},{"range":"M97","value":0.1,"horizontalAlignment":"general-right"},{"range":"A98","value":"wineblock42"},{"range":"B98","value":"blockchild"},{"range":"C98","value":"block"},{"range":"D98","value":"::scene::"},{"range":"E98","value":0,"horizontalAlignment":"general-right"},{"range":"F98","value":5,"horizontalAlignment":"general-right"},{"range":"G98","value":-16,"horizontalAlignment":"general-right"},{"range":"H98","value":"-90deg"},{"range":"I98","value":"-90deg"},{"range":"K98","value":0.1,"horizontalAlignment":"general-right"},{"range":"L98","value":0.1,"horizontalAlignment":"general-right"},{"range":"M98","value":0.1,"horizontalAlignment":"general-right"},{"range":"A99","value":"wineblock43"},{"range":"B99","value":"blockchild"},{"range":"C99","value":"block"},{"range":"D99","value":"::scene::"},{"range":"E99","value":0,"horizontalAlignment":"general-right"},{"range":"F99","value":5,"horizontalAlignment":"general-right"},{"range":"G99","value":-18,"horizontalAlignment":"general-right"},{"range":"H99","value":"-90deg"},{"range":"I99","value":"-90deg"},{"range":"K99","value":0.1,"horizontalAlignment":"general-right"},{"range":"L99","value":0.1,"horizontalAlignment":"general-right"},{"range":"M99","value":0.1,"horizontalAlignment":"general-right"},{"range":"A100","value":"wineblock44"},{"range":"B100","value":"blockchild"},{"range":"C100","value":"block"},{"range":"D100","value":"::scene::"},{"range":"E100","value":0,"horizontalAlignment":"general-right"},{"range":"F100","value":5,"horizontalAlignment":"general-right"},{"range":"G100","value":-20,"horizontalAlignment":"general-right"},{"range":"H100","value":"-90deg"},{"range":"I100","value":"-90deg"},{"range":"K100","value":0.1,"horizontalAlignment":"general-right"},{"range":"L100","value":0.1,"horizontalAlignment":"general-right"},{"range":"M100","value":0.1,"horizontalAlignment":"general-right"},{"range":"A101","value":"wineblock5"},{"range":"B101","value":"blockchild"},{"range":"C101","value":"block"},{"range":"D101","value":"::scene::"},{"range":"E101","value":0,"horizontalAlignment":"general-right"},{"range":"F101","value":5,"horizontalAlignment":"general-right"},{"range":"G101","value":-24,"horizontalAlignment":"general-right"},{"range":"H101","value":"-90deg"},{"range":"I101","value":"-90deg"},{"range":"K101","value":0.1,"horizontalAlignment":"general-right"},{"range":"L101","value":0.1,"horizontalAlignment":"general-right"},{"range":"M101","value":0.1,"horizontalAlignment":"general-right"},{"range":"A102","value":"wineblock52"},{"range":"B102","value":"blockchild"},{"range":"C102","value":"block"},{"range":"D102","value":"::scene::"},{"range":"E102","value":0,"horizontalAlignment":"general-right"},{"range":"F102","value":5,"horizontalAlignment":"general-right"},{"range":"G102","value":-26,"horizontalAlignment":"general-right"},{"range":"H102","value":"-90deg"},{"range":"I102","value":"-90deg"},{"range":"K102","value":0.1,"horizontalAlignment":"general-right"},{"range":"L102","value":0.1,"horizontalAlignment":"general-right"},{"range":"M102","value":0.1,"horizontalAlignment":"general-right"},{"range":"A103","value":"wineblock53"},{"range":"B103","value":"blockchild"},{"range":"C103","value":"block"},{"range":"D103","value":"::scene::"},{"range":"E103","value":0,"horizontalAlignment":"general-right"},{"range":"F103","value":5,"horizontalAlignment":"general-right"},{"range":"G103","value":-28,"horizontalAlignment":"general-right"},{"range":"H103","value":"-90deg"},{"range":"I103","value":"-90deg"},{"range":"K103","value":0.1,"horizontalAlignment":"general-right"},{"range":"L103","value":0.1,"horizontalAlignment":"general-right"},{"range":"M103","value":0.1,"horizontalAlignment":"general-right"},{"range":"A104","value":"wineblock7"},{"range":"B104","value":"blockchild"},{"range":"C104","value":"block"},{"range":"D104","value":"::scene::"},{"range":"E104","value":0,"horizontalAlignment":"general-right"},{"range":"F104","value":5,"horizontalAlignment":"general-right"},{"range":"G104","value":10,"horizontalAlignment":"general-right"},{"range":"H104","value":"-90deg"},{"range":"I104","value":"-90deg"},{"range":"K104","value":0.1,"horizontalAlignment":"general-right"},{"range":"L104","value":0.1,"horizontalAlignment":"general-right"},{"range":"M104","value":0.1,"horizontalAlignment":"general-right"},{"range":"A105","value":"wineblock72"},{"range":"B105","value":"blockchild"},{"range":"C105","value":"block"},{"range":"D105","value":"::scene::"},{"range":"E105","value":0,"horizontalAlignment":"general-right"},{"range":"F105","value":5,"horizontalAlignment":"general-right"},{"range":"G105","value":13,"horizontalAlignment":"general-right"},{"range":"H105","value":"-90deg"},{"range":"I105","value":"-90deg"},{"range":"K105","value":0.1,"horizontalAlignment":"general-right"},{"range":"L105","value":0.1,"horizontalAlignment":"general-right"},{"range":"M105","value":0.1,"horizontalAlignment":"general-right"},{"range":"A106","value":"wineblock73"},{"range":"B106","value":"blockchild"},{"range":"C106","value":"block"},{"range":"D106","value":"::scene::"},{"range":"E106","value":0,"horizontalAlignment":"general-right"},{"range":"F106","value":5,"horizontalAlignment":"general-right"},{"range":"G106","value":16,"horizontalAlignment":"general-right"},{"range":"H106","value":"-90deg"},{"range":"I106","value":"-90deg"},{"range":"K106","value":0.1,"horizontalAlignment":"general-right"},{"range":"L106","value":0.1,"horizontalAlignment":"general-right"},{"range":"M106","value":0.1,"horizontalAlignment":"general-right"},{"range":"A107","value":"wineblock74"},{"range":"B107","value":"blockchild"},{"range":"C107","value":"block"},{"range":"D107","value":"::scene::"},{"range":"E107","value":0,"horizontalAlignment":"general-right"},{"range":"F107","value":5,"horizontalAlignment":"general-right"},{"range":"G107","value":19,"horizontalAlignment":"general-right"},{"range":"H107","value":"-90deg"},{"range":"I107","value":"-90deg"},{"range":"K107","value":0.1,"horizontalAlignment":"general-right"},{"range":"L107","value":0.1,"horizontalAlignment":"general-right"},{"range":"M107","value":0.1,"horizontalAlignment":"general-right"},{"range":"A1"}]
